pycharsheet/__init__.py
pycharsheet/__main__.py
pycharsheet/_meta.py
pycharsheet/charsheet.py
pycharsheet/error.py
pycharsheet/cli/__init__.py
pycharsheet/cli/commands.py
pycharsheet/cli/error.py
pycharsheet/gui/__init__.py
pycharsheet/gui/frame.py
pycharsheet-0.0.4.dist-info/DESCRIPTION.rst
pycharsheet-0.0.4.dist-info/METADATA
pycharsheet-0.0.4.dist-info/RECORD
pycharsheet-0.0.4.dist-info/WHEEL
pycharsheet-0.0.4.dist-info/entry_points.txt
pycharsheet-0.0.4.dist-info/metadata.json
pycharsheet-0.0.4.dist-info/top_level.txt
