Metadata-Version: 2.0
Name: pycharsheet
Version: 0.0.4
Summary: A library and utility for managing a role playing game character sheet and some character state as well
Home-page: https://gitlab.com/Taywee/pycharsheet
Author: Taylor C. Richberger and Brandon Phillips
License: MIT
Keywords: dnd dungeons dragons rpg game utility
Platform: UNKNOWN
Classifier: Development Status :: 2 - Pre-Alpha
Classifier: Programming Language :: Python :: 3
Classifier: Programming Language :: Python :: 3.6
Classifier: Operating System :: OS Independent
Classifier: License :: OSI Approved :: MIT License
Classifier: License :: OSI Approved :: MIT License
Classifier: Topic :: Utilities
Classifier: Topic :: Games/Entertainment
Classifier: Topic :: Games/Entertainment :: Role-Playing
Requires-Dist: lupa (==1.8)
Requires-Dist: packaging (==19.1)
Requires-Dist: pathlib2 (==2.3.4)
Requires-Dist: wxPython (==4.0.6)
